pape_mcp_server_time/__init__.py
pape_mcp_server_time/__main__.py
pape_mcp_server_time/server.py
pape_mcp_server_time-0.6.3.dist-info/METADATA
pape_mcp_server_time-0.6.3.dist-info/WHEEL
pape_mcp_server_time-0.6.3.dist-info/entry_points.txt
pape_mcp_server_time-0.6.3.dist-info/RECORD
