Metadata-Version: 2.4
Name: pape-mcp-server-time
Version: 0.6.3
Summary: A Model Context Protocol server providing tools for time queries and timezone conversions for LLMs
Author-email: Carter Pape <pape-mcp-server-time@carterpape.com>, Mariusz 'maledorak' Korzekwa <mariusz@korzekwa.dev>
License: MIT
Keywords: llm,mcp,time,timezone
Classifier: Intended Audience :: Developers
Classifier: License :: OSI Approved :: MIT License
Classifier: Programming Language :: Python :: 3
Requires-Python: >=3.10
Requires-Dist: mcp>=1.0.0
Requires-Dist: pydantic>=2.0.0
Requires-Dist: tzdata>=2024.2
Requires-Dist: tzlocal>=5.2
